crcany-0.2.1.dist-info/RECORD
crcany-0.2.1.dist-info/LICENSE
crcany-0.2.1.dist-info/WHEEL
crcany-0.2.1.dist-info/top_level.txt
crcany-0.2.1.dist-info/METADATA
crcany/crcany.pyx
crcany/models.py
crcany/__init__.py
crcany/crcany.cpython-39-darwin.so
