Metadata-Version: 2.1
Name: crcany
Version: 0.2.1
Summary: Python CRC Computation Library
Project-URL: Homepage, https://github.com/marzooqy/crcany
Requires-Python: >=3.7
License-File: LICENSE
